UzEduCorpus/UzEduCorpus.py
UzEduCorpus/__init__.py
UzEduCorpus/grade_1.csv
UzEduCorpus/grade_2.csv
UzEduCorpus/grade_3.csv
UzEduCorpus/grade_4.csv
UzEduCorpus/grade_5.csv
UzEduCorpus/grade_6.csv
UzEduCorpus/grade_7.csv
UzEduCorpus/grade_8.csv
UzEduCorpus/grade_9.csv
UzEduCorpus-0.0.4.dist-info/LICENSE
UzEduCorpus-0.0.4.dist-info/METADATA
UzEduCorpus-0.0.4.dist-info/WHEEL
UzEduCorpus-0.0.4.dist-info/top_level.txt
UzEduCorpus-0.0.4.dist-info/RECORD
