Metadata-Version: 2.1
Name: UzEduCorpus
Version: 0.0.4
Summary: Uzbek language Educational Corpus
Home-page: https://uzedu.uz/uz
Author: Muhayyo Narimonova
Author-email: muhayyonarimonova1797@gmail.com
Project-URL: Bug Tracker, https://uzedu.uz/uz
Keywords: python,uzbek-language,latin
Classifier: Programming Language :: Python :: 3
Classifier: License :: OSI Approved :: MIT License
Classifier: Operating System :: OS Independent
Requires-Python: >=3.6
License-File: LICENSE
